qs2csv/__init__.py
qs2csv/export.py
django_qs2csv-0.3.5.dist-info/LICENSE
django_qs2csv-0.3.5.dist-info/METADATA
django_qs2csv-0.3.5.dist-info/WHEEL
django_qs2csv-0.3.5.dist-info/top_level.txt
django_qs2csv-0.3.5.dist-info/RECORD
