Metadata-Version: 2.1
Name: django-qs2csv
Version: 0.3.5
Summary: A simple package to convert a Django QuerySet to a CSV file through an HttpResponse object.
Author-email: Jer-Pha <pharesoft@gmail.com>
Project-URL: Homepage, https://github.com/Jer-Pha/django-qs2csv
Project-URL: Issues, https://github.com/Jer-Pha/django-qs2csv/issues
Keywords: django,csv,export,httpresponse,http response,pandas
Classifier: Development Status :: 3 - Alpha
Classifier: Intended Audience :: Developers
Classifier: Environment :: Web Environment
Classifier: Framework :: Django
Classifier: Framework :: Django :: 3
Classifier: Framework :: Django :: 3.2
Classifier: Framework :: Django :: 4
Classifier: Framework :: Django :: 4.0
Classifier: Framework :: Django :: 4.1
Classifier: Framework :: Django :: 4.2
Classifier: Framework :: Django :: 5.0
Classifier: Framework :: Django :: 5.1
Classifier: Programming Language :: Python :: 3
Classifier: License :: OSI Approved :: MIT License
Classifier: Natural Language :: English
Classifier: Operating System :: OS Independent
Classifier: Programming Language :: Python :: 3
Classifier: Programming Language :: Python :: 3.9
Classifier: Programming Language :: Python :: 3.10
Classifier: Programming Language :: Python :: 3.11
Classifier: Programming Language :: Python :: 3.12
Classifier: Programming Language :: Python :: 3.13
Classifier: Topic :: File Formats
Classifier: Topic :: Internet :: WWW/HTTP
Classifier: Topic :: Office/Business :: Financial :: Spreadsheet
Classifier: Topic :: Software Development :: Libraries :: Python Modules
Requires-Python: >=3.9
License-File: LICENSE
Requires-Dist: django >=3.2
Requires-Dist: importlib-metadata ; python_version < "3.10"
Provides-Extra: pd
Requires-Dist: pandas >=1.5 ; extra == 'pd'
